text2resume/__init__.py
text2resume/generate_resume.py
text2resume/templates/template.tex
text2resume-0.3.dist-info/LICENSE
text2resume-0.3.dist-info/METADATA
text2resume-0.3.dist-info/WHEEL
text2resume-0.3.dist-info/entry_points.txt
text2resume-0.3.dist-info/top_level.txt
text2resume-0.3.dist-info/RECORD
