Metadata-Version: 2.1
Name: text2resume
Version: 0.3
Summary: A module to generate PDFs from YAML data
Home-page: https://github.com/rishi-m100/text2resume
Author: Rishi Mulchandani
Author-email: rishimulchandani100@gmail.com
Classifier: Programming Language :: Python :: 3
Classifier: License :: OSI Approved :: MIT License
Classifier: Operating System :: OS Independent
Requires-Python: >=3.6
License-File: LICENSE
Requires-Dist: PyYAML
Requires-Dist: Jinja2
